nyc_prop_prediction/__init__.py
nyc_prop_prediction/__main__.py
nyc_prop_prediction/_version.py
nyc_prop_prediction/inputmodel_grad.joblib
nyc_prop_prediction/nyc_prop_prediction.py
nyc_prop_prediction/zipmodel_grad.joblib
nyc_prop_prediction-0.1.4.dist-info/LICENSE
nyc_prop_prediction-0.1.4.dist-info/METADATA
nyc_prop_prediction-0.1.4.dist-info/WHEEL
nyc_prop_prediction-0.1.4.dist-info/top_level.txt
nyc_prop_prediction-0.1.4.dist-info/RECORD
